ducklingscript/__init__.py
ducklingscript/__main__.py
ducklingscript/cli/__init__.py
ducklingscript/cli/all.py
ducklingscript/cli/app.py
ducklingscript/cli/compile.py
ducklingscript/cli/components/__init__.py
ducklingscript/cli/components/cli_component.py
ducklingscript/cli/components/compile_component.py
ducklingscript/cli/help.py
ducklingscript/cli/interpret.py
ducklingscript/cli/new.py
ducklingscript/cli/utils/__init__.py
ducklingscript/cli/utils/command_format.py
ducklingscript/cli/utils/config.py
ducklingscript/cli/version.py
ducklingscript/compiler/__init__.py
ducklingscript/compiler/commands/__init__.py
ducklingscript/compiler/commands/alt.py
ducklingscript/compiler/commands/arrow_keys.py
ducklingscript/compiler/commands/bases/__init__.py
ducklingscript/compiler/commands/bases/base_command.py
ducklingscript/compiler/commands/bases/block_command.py
ducklingscript/compiler/commands/bases/doc_command.py
ducklingscript/compiler/commands/bases/simple_command.py
ducklingscript/compiler/commands/break_loop.py
ducklingscript/compiler/commands/continue_loop.py
ducklingscript/compiler/commands/ctrl.py
ducklingscript/compiler/commands/default_delay.py
ducklingscript/compiler/commands/delay.py
ducklingscript/compiler/commands/enter.py
ducklingscript/compiler/commands/exist.py
ducklingscript/compiler/commands/extended.py
ducklingscript/compiler/commands/flipper_altchar.py
ducklingscript/compiler/commands/flipper_altcode.py
ducklingscript/compiler/commands/flipper_altstring.py
ducklingscript/compiler/commands/flipper_default_string_delay.py
ducklingscript/compiler/commands/flipper_device_id.py
ducklingscript/compiler/commands/flipper_hold_release.py
ducklingscript/compiler/commands/flipper_media.py
ducklingscript/compiler/commands/flipper_modifier_keys.py
ducklingscript/compiler/commands/flipper_mouse_click.py
ducklingscript/compiler/commands/flipper_mouse_move.py
ducklingscript/compiler/commands/flipper_mouse_scroll.py
ducklingscript-0.2.3.dist-info/entry_points.txt
ducklingscript-0.2.3.dist-info/LICENSE
ducklingscript-0.2.3.dist-info/METADATA
ducklingscript-0.2.3.dist-info/NOTICE
ducklingscript-0.2.3.dist-info/WHEEL
ducklingscript-0.2.3.dist-info/RECORD
