Metadata-Version: 2.3
Name: ducklingscript
Version: 0.2.3
Summary: A transcompiler for converting DucklingScript code into Rubber Ducky Language 1.0
Keywords: duckyscript,flipper,ducky,key injection
Author: Dragon of Shuu
Author-email: loganmcederlof@gmail.com
Requires-Python: >=3.11,<4.0
Classifier: Programming Language :: Python :: 3
Classifier: Programming Language :: Python :: 3.11
Classifier: Programming Language :: Python :: 3.12
Classifier: Programming Language :: Python :: 3.13
Requires-Dist: pyyaml (>=6.0.1,<7.0.0)
Requires-Dist: quackinter (>=0.2.1.1,<0.3.0.0)
Requires-Dist: setuptools (>=69.0.2,<70.0.0)
Requires-Dist: typer[all] (>=0.15.4,<0.16.0)
Project-URL: Documentation, https://ducklingscript.dragonofshuu.dev/
Project-URL: DragonOfShuu.dev, https://dragonofshuu.dev/
Project-URL: Repository, https://github.com/DragonOfShuu/DucklingScript/
